VerdisCloudPackage/AWS.py
VerdisCloudPackage/__init__.py
VerdisCloudPackage-0.0.9.dist-info/LICENSE.txt
VerdisCloudPackage-0.0.9.dist-info/METADATA
VerdisCloudPackage-0.0.9.dist-info/WHEEL
VerdisCloudPackage-0.0.9.dist-info/top_level.txt
VerdisCloudPackage-0.0.9.dist-info/RECORD
